botflow/__init__.py
botflow/base.py
botflow/bdata.py
botflow/bot.py
botflow/botbase.py
botflow/botflow.py
botflow/botframe.py
botflow/config.py
botflow/function.py
botflow/functionbase.py
botflow/node.py
botflow/nodebase.py
botflow/pipe.py
botflow/queue.py
botflow/route.py
botflow/routebase.py
botflow/ex/__init__.py
botflow/ex/aiofile.py
botflow/ex/http.py
botflow-0.2.0.dist-info/METADATA
botflow-0.2.0.dist-info/RECORD
botflow-0.2.0.dist-info/WHEEL
botflow-0.2.0.dist-info/top_level.txt
