Metadata-Version: 2.1
Name: botflow
Version: 0.2.0
Summary: Data-driven and Reactive  programming framework 
Home-page: https://github.com/kkyx/botflow
Author: Guojian Li
Author-email: guojianlee@gmail.com
License: BSD
Platform: UNKNOWN
Classifier: Development Status :: 3 - Alpha
Classifier: Intended Audience :: Developers
Classifier: License :: OSI Approved :: BSD License
Classifier: Programming Language :: Python :: 3
Requires-Python: >=3.6.5
Requires-Dist: aiohttp (>=3.3.0)
Requires-Dist: graphviz
Requires-Dist: beautifulsoup4
Requires-Dist: lxml
